vaga/__init__.py
vaga-0.0.1.dist-info/METADATA
vaga-0.0.1.dist-info/WHEEL
vaga-0.0.1.dist-info/RECORD
