Metadata-Version: 2.4
Name: vaga
Version: 0.0.1
Summary: Python library for the Vaga Link API.
Project-URL: homepage, https://vagaslink.com/
Project-URL: source, https://github.com/laurentino-co/vaga-python
Project-URL: issues, https://github.com/laurentino-co/vaga-python/issues
Author-email: Emerson Laurentino <emerson@laurentino.co>
License: MIT
Classifier: Development Status :: 1 - Planning
Classifier: License :: OSI Approved :: MIT License
Classifier: Operating System :: OS Independent
Classifier: Programming Language :: Python :: 3
Requires-Python: >=3.8
